l298n_driver/IO_Types.py
l298n_driver/L298N.py
l298n_driver/__init__.py
l298n_driver-0.1.0.dist-info/METADATA
l298n_driver-0.1.0.dist-info/WHEEL
l298n_driver-0.1.0.dist-info/licenses/LICENSE
l298n_driver-0.1.0.dist-info/RECORD
