Metadata-Version: 2.3
Name: l298n_driver
Version: 0.1.0
Summary: Python interface for l298n h-bridge motor driver
Project-URL: Homepage, https://github.com/T-N-S/l298n_driver
Author-email: Tim Schumann <gerb008701@gmail.com>
License-File: LICENSE
